housefullcode/__init__.py
housefullcode/core.py
housefullcode-0.5.0.dist-info/licenses/LICENSE
housefullcode-0.5.0.dist-info/METADATA
housefullcode-0.5.0.dist-info/WHEEL
housefullcode-0.5.0.dist-info/top_level.txt
housefullcode-0.5.0.dist-info/RECORD
