Metadata-Version: 2.4
Name: housefullcode
Version: 0.5.0
Summary: House full code
Author-email: Untying-Cage1 <housefull420boys@gmail.com>
License: MIT
Project-URL: Homepage, https://github.com/housefull420/TL.git
Classifier: Programming Language :: Python :: 3
Classifier: License :: OSI Approved :: MIT License
Classifier: Operating System :: OS Independent
Requires-Python: >=3.7
License-File: LICENSE
Dynamic: license-file
